discord_c2/__init__.py
discord_c2/cdn.py
discord_c2/webhooks.py
discord_c2-0.0.2.dist-info/LICENSE
discord_c2-0.0.2.dist-info/METADATA
discord_c2-0.0.2.dist-info/WHEEL
discord_c2-0.0.2.dist-info/top_level.txt
discord_c2-0.0.2.dist-info/RECORD
