Metadata-Version: 2.1
Name: discord-c2
Version: 0.0.2
Summary: A package to interact with discord webhooks/pull-down files from Discord's CDN
Author-email: Evan Huff <ehuff007@gmail.com>
Classifier: Programming Language :: Python :: 3
Classifier: License :: OSI Approved :: MIT License
Classifier: Operating System :: OS Independent
Requires-Python: >=3.7
License-File: LICENSE
